milvus_dataset-1.0.0.post47.dist-info/METADATA
milvus_dataset-1.0.0.post47.dist-info/WHEEL
milvus_dataset-1.0.0.post47.dist-info/entry_points.txt
milvus_dataset/__init__.py
milvus_dataset/__version__.py
milvus_dataset/api/main.py
milvus_dataset/core.py
milvus_dataset/log_config.py
milvus_dataset/neighbors.py
milvus_dataset/reader.py
milvus_dataset/storage.py
milvus_dataset/utils.py
milvus_dataset/web/app.py
milvus_dataset/writer.py
milvus_dataset-1.0.0.post47.dist-info/RECORD
