Metadata-Version: 2.1
Name: milvus-dataset
Version: 1.0.0.post47
Summary: Default template for PDM package
Author-Email: zhuwenxing <wenxing.zhu@zilliz.com>
License: MIT
Requires-Python: >=3.10
Requires-Dist: pydantic>=2.10.3
Requires-Dist: pandas>=2.2.3
Requires-Dist: fsspec>=2024.10.0
Requires-Dist: pyarrow>=18.1.0
Requires-Dist: s3fs>=2024.10.0
Requires-Dist: gcsfs>=2024.10.0
Requires-Dist: tqdm>=4.67.1
Requires-Dist: loguru>=0.7.3
Requires-Dist: scikit-learn>=1.6.0
Requires-Dist: pymilvus>=2.5.0
Requires-Dist: numba>=0.60.0
Requires-Dist: datasets>=2.14.4
Requires-Dist: colorama>=0.4.6
Requires-Dist: ml-dtypes
Requires-Dist: faker>=33.1.0
Requires-Dist: modelscope>=1.21.0
Requires-Dist: h5py>=3.12.1
Requires-Dist: usearch>=2.12.0
Provides-Extra: gpu
Requires-Dist: cupy-cuda12x==13.3.0; extra == "gpu"
Requires-Dist: cuvs-cu12==24.12.0; extra == "gpu"
Provides-Extra: api
Requires-Dist: fastapi>=0.115.6; extra == "api"
Requires-Dist: uvicorn>=0.34.0; extra == "api"
Requires-Dist: python-multipart>=0.0.20; extra == "api"
Provides-Extra: web
Requires-Dist: streamlit>=1.41.1; extra == "web"
